thebrukhellomodule/__init__.py
thebrukhellomodule/emojier.py
thebrukhellomodule-5.0.dist-info/METADATA
thebrukhellomodule-5.0.dist-info/WHEEL
thebrukhellomodule-5.0.dist-info/top_level.txt
thebrukhellomodule-5.0.dist-info/RECORD
