Metadata-Version: 2.1
Name: thebrukhellomodule
Version: 5.0
Summary: Hello!
Home-page: UNKNOWN
Author: UNKNOWN
Author-email: thebrukprojects@gmail.com
License: UNKNOWN
Platform: UNKNOWN
